{"id":"2472585b-e41d-4a49-9190-c4cde93b3d41","source":"d:a a 0\n  sg:4 4 40 2\n    tr:0.5u 1u\n      p:2ux b:0 2u 1.5u 0 1.5u 0,-1u2 -2u 1u 0","svg":"<svg xmlns=\"http://www.w3.org/2000/svg\" class=\"renderer-svg\" height=\"160\" width=\"160\" fill=\"#000000\" viewBox=\"0 0 160 160\"><g transform=\"translate(0, 0)\"><g transform=\"translate(20 40)\"><path d=\"M 80 0 M 80 0 c 60,0 60,80 0,80 s 40,0 -80,-80\" fill-rule=\"evenodd\"></path></g></g></svg>","name":"Cold Turbo Spring","group":"ungrouped","modified":"2020-03-16T03:20:08.799Z","created":"2020-01-29T22:19:49.020Z","padding":0,"thumb":"2472585b-e41d-4a49-9190-c4cde93b3d41.png","ratio":1}