{"id":"b9d5b686-1247-4a79-837c-a7354ef5a65e","source":"d:a a 0\n  sg:4 4 40 1\n  p:2u 0,a:1uy pi,+:-0.5uy,a:-0.5uy pi f ,0.5uy pi f,+:0.5uy,-\n  a:1uy pi f,-2uy pi\n   ci:2u 3u 0.5u","svg":"<svg xmlns=\"http://www.w3.org/2000/svg\" class=\"renderer-svg\" height=\"160\" width=\"160\" fill=\"#000000\" viewBox=\"0 0 160 160\"><g transform=\"translate(0, 0)\"><path d=\"M 80 0 L 80 0 A 40 40 0 0 0 80 80 l 0 -20 L 80 60 A 20 20 0 0 1 80 20 L 80 20 A 20 20 0 0 1 80 60 l 0 20 L 80 80 A 40 40 0 0 1 80 160 L 80 160 A 80 80 0 0 0 79.99999999999999 0\" fill-rule=\"evenodd\"></path><circle cx=\"80\" cy=\"120\" r=\"20\"></circle></g></svg>","name":"Stream Shine Silver","group":"ungrouped","modified":"2021-11-11T03:34:58.291Z","created":"2021-11-10T07:38:07.327Z","padding":0,"thumb":"b9d5b686-1247-4a79-837c-a7354ef5a65e.png","ratio":1}